django_admin_keyshortcuts/__init__.py
django_admin_keyshortcuts/static/admin/css/shortcuts.css
django_admin_keyshortcuts/static/admin/js/shortcuts.js
django_admin_keyshortcuts/static/admin/js/shortcuts_changelist.js
django_admin_keyshortcuts/static/admin/js/vendor/hotkey/hotkey.js
django_admin_keyshortcuts/templates/admin/base.html
django_admin_keyshortcuts/templates/admin/change_form.html
django_admin_keyshortcuts/templates/admin/change_form_shortcuts.html
django_admin_keyshortcuts/templates/admin/change_list.html
django_admin_keyshortcuts/templates/admin/change_list_shortcuts.html
django_admin_keyshortcuts/templates/admin/delete_confirmation.html
django_admin_keyshortcuts/templates/admin/delete_confirmation_shortcuts.html
django_admin_keyshortcuts/templates/admin/delete_selected_confirmation.html
django_admin_keyshortcuts/templates/admin/login.html
django_admin_keyshortcuts/templates/admin/nav_sidebar.html
django_admin_keyshortcuts/templates/admin/search_form.html
django_admin_keyshortcuts/templates/admin/shortcuts.html
django_admin_keyshortcuts/templates/admin/submit_line.html
django_admin_keyshortcuts/templatetags/__init__.py
django_admin_keyshortcuts/templatetags/shortcuts.py
django_admin_keyshortcuts-0.2.2.dist-info/WHEEL
django_admin_keyshortcuts-0.2.2.dist-info/METADATA
django_admin_keyshortcuts-0.2.2.dist-info/RECORD
