Metadata-Version: 2.3
Name: django-admin-keyshortcuts
Version: 0.2.2
Summary: Keyboard shortcuts for Django Admin
Author: Tom Carrick, A. Rafey Khan
Author-email: Tom Carrick <tom@carrick.eu>, A. Rafey Khan <khanxbahria@gmail.com>
Requires-Dist: django>=4.2
Requires-Python: >=3.9
